known_side_effects/__init__.py
known_side_effects/argument_matcher.py
known_side_effects/exceptions.py
known_side_effects/types.py
known_side_effects/matchers/__init__.py
known_side_effects/matchers/parameter_matchers.py
known_side_effects/matchers/types.py
known_side_effects-0.1.1.dist-info/LICENSE
known_side_effects-0.1.1.dist-info/METADATA
known_side_effects-0.1.1.dist-info/WHEEL
known_side_effects-0.1.1.dist-info/top_level.txt
known_side_effects-0.1.1.dist-info/RECORD
