Metadata-Version: 2.1
Name: known-side-effects
Version: 0.1.1
Summary: A test utility library to help write explict side effects for mocked objects
Home-page: https://github.com/P4rk/known_side_effects
Author: Luke Park
Author-email: luke@p4rk.dev
License: UNKNOWN
Platform: UNKNOWN
Classifier: Programming Language :: Python :: 3 :: Only
Classifier: Programming Language :: Python :: 3.6
Classifier: Programming Language :: Python :: 3.7
Classifier: Programming Language :: Python :: 3.8
Classifier: License :: OSI Approved :: MIT License
Classifier: Operating System :: OS Independent
Classifier: Topic :: Software Development :: Testing
Requires-Dist: PyHamcrest (>=1.9.0)
